datasets/__init__.py
datasets/coco.py
datasets/ds_utils.py
datasets/factory.py
datasets/imagenet.py
datasets/imdb.py
datasets/pascal_voc.py
datasets/pascal_voc_rbg.py
datasets/vg.py
datasets/vg_eval.py
datasets/voc_eval.py
datasets/voc_eval_raw.py
model/__init__.py
model/faster_rcnn/__init__.py
model/faster_rcnn/faster_rcnn.py
model/faster_rcnn/resnet.py
model/faster_rcnn/vgg16.py
model/nms/__init__.py
model/nms/build.py
model/nms/nms_cpu.py
model/nms/nms_gpu.py
model/nms/nms_wrapper.py
model/nms/_ext/__init__.py
model/nms/_ext/nms/__init__.py
model/roi_align/__init__.py
model/roi_align/build.py
model/roi_align/_ext/__init__.py
model/roi_align/_ext/roi_align/__init__.py
model/roi_align/functions/__init__.py
model/roi_align/functions/roi_align.py
model/roi_align/modules/__init__.py
model/roi_align/modules/roi_align.py
model/roi_crop/__init__.py
model/roi_crop/build.py
model/roi_crop/_ext/__init__.py
model/roi_crop/_ext/crop_resize/__init__.py
model/roi_crop/_ext/roi_crop/__init__.py
model/roi_crop/functions/__init__.py
model/roi_crop/functions/crop_resize.py
model/roi_crop/functions/gridgen.py
model/roi_crop/functions/roi_crop.py
model/roi_crop/modules/__init__.py
model/roi_crop/modules/gridgen.py
model/roi_crop/modules/roi_crop.py
model/roi_layers/__init__.py
model/roi_layers/nms.py
model/roi_layers/roi_align.py
model/roi_layers/roi_pool.py
model/roi_pooling/__init__.py
model/roi_pooling/build.py
model/roi_pooling/_ext/__init__.py
model/roi_pooling/_ext/roi_pooling/__init__.py
model/roi_pooling/functions/__init__.py
model/roi_pooling/functions/roi_pool.py
model/roi_pooling/modules/__init__.py
model/roi_pooling/modules/roi_pool.py
model/rpn/__init__.py
model/rpn/anchor_target_layer.py
model/rpn/bbox_transform.py
model/rpn/generate_anchors.py
model/rpn/proposal_layer.py
model/rpn/proposal_target_layer_cascade.py
model/rpn/rpn.py
model/utils/__init__.py
model/utils/blob.py
model/utils/config.py
model/utils/logger.py
model/utils/matching.py
model/utils/net_utils.py
handObjectacb-0.1.3.dist-info/LICENSE
handObjectacb-0.1.3.dist-info/METADATA
handObjectacb-0.1.3.dist-info/WHEEL
handObjectacb-0.1.3.dist-info/top_level.txt
handObjectacb-0.1.3.dist-info/RECORD
