Metadata-Version: 2.1
Name: handObjectacb
Version: 0.1.3
Summary: HandObject
Home-page: UNKNOWN
Author: Andreu Crespo
Author-email: ancrebar@i3b.upv.es
License: UNKNOWN
Platform: UNKNOWN
Classifier: Programming Language :: Python :: 3
Classifier: License :: OSI Approved :: MIT License
Classifier: Operating System :: OS Independent
Requires-Python: >=3
License-File: LICENSE
Requires-Dist: certifi (>=2021.5.30)
Requires-Dist: colorama (>=0.4.4)
Requires-Dist: cycler (>=0.10.0)
Requires-Dist: Cython (>=0.29.23)
Requires-Dist: Jinja2
Requires-Dist: kiwisolver (>=1.3.1)
Requires-Dist: MarkupSafe
Requires-Dist: matplotlib (>=3.3.4)
Requires-Dist: msgpack (>=1.0.2)
Requires-Dist: olefile (>=0.46)
Requires-Dist: opencv-python (>=4.5.2.54)
Requires-Dist: pascal-voc-writer (>=0.1.4)
Requires-Dist: protobuf (>=3.17.3)
Requires-Dist: pyparsing (>=2.4.7)
Requires-Dist: python-dateutil (>=2.8.1)
Requires-Dist: PyYAML (>=5.4.1)
Requires-Dist: scipy (>=1.5.4)
Requires-Dist: tensorboardX (>=2.4)
Requires-Dist: torch (==1.8.0)
Requires-Dist: torchaudio (==0.8.0)
Requires-Dist: torchvision (==0.9.0)
Requires-Dist: tqdm (>=4.61.2)
Requires-Dist: wincertstore (>=0.2)
